getkey
tests
tools
