Metadata-Version: 1.1
Name: getkey
Version: 0.6.2
Summary: Utilities to read single characters and key-strokes
Home-page: https://github.com/kcsaff/getkey
Author: K.C.Saff
Author-email: kc@saff.net
License: MIT
Keywords: stdin,command line
Platform: UNKNOWN
Classifier: Development Status :: 5 - Production/Stable
Classifier: Environment :: Console
Classifier: Intended Audience :: Developers
Classifier: License :: OSI Approved :: MIT License
Classifier: Operating System :: OS Independent
Classifier: Programming Language :: Python :: 2.7
Classifier: Programming Language :: Python :: 3.3
Classifier: Programming Language :: Python :: 3.4
Classifier: Programming Language :: Python :: 3.5
Classifier: Topic :: Software Development
Classifier: Topic :: Software Development :: User Interfaces
